fNIRS-BIDS-Validator/__init__.py
fNIRS-BIDS-Validator/fNIRS_BIDS.py
fNIRS-BIDS-Validator/fNIRS_BIDS_validator.py
fNIRS-BIDS-Validator/setup.py
fNIRS-BIDS-Validator/update_fNIRS_BIDS_schema.py
fNIRS_BIDS_Validator/BIDS_fNIRS_subject_folder.json
fNIRS_BIDS_Validator/BIDS_raw_folder.json
fNIRS_BIDS_Validator/__init__.py
fNIRS_BIDS_Validator/fNIRS_BIDS.py
fNIRS_BIDS_Validator/fNIRS_BIDS_validator.py
fNIRS_BIDS_Validator/setup.py
fNIRS_BIDS_Validator/update_fNIRS_BIDS_schema.py
fNIRS_BIDS_Validator-0.0.9.dist-info/METADATA
fNIRS_BIDS_Validator-0.0.9.dist-info/RECORD
fNIRS_BIDS_Validator-0.0.9.dist-info/WHEEL
fNIRS_BIDS_Validator-0.0.9.dist-info/top_level.txt
