Metadata-Version: 2.1
Name: fNIRS-BIDS-Validator
Version: 0.0.9
Summary: fNIRS BIDS Validator
Home-page: UNKNOWN
Author: Sreekanth Kura
Author-email: <sreekanth.kura7@gmail.com>
License: UNKNOWN
Keywords: python,fNIRS-BIDS,fNIRS,BIDS
Platform: UNKNOWN
Classifier: Development Status :: 3 - Alpha
Classifier: Intended Audience :: Developers
Classifier: Programming Language :: Python :: 3
Classifier: Operating System :: Unix
Classifier: Operating System :: MacOS :: MacOS X
Classifier: Operating System :: Microsoft :: Windows
Requires-Dist: pandas
Requires-Dist: pysnirf2
Requires-Dist: importlib-resources
